transmission_rpc/__init__.py
transmission_rpc/client.py
transmission_rpc/constants.py
transmission_rpc/error.py
transmission_rpc/py.typed
transmission_rpc/session.py
transmission_rpc/torrent.py
transmission_rpc/types.py
transmission_rpc/utils.py
transmission_rpc-7.0.11.dist-info/LICENSE
transmission_rpc-7.0.11.dist-info/WHEEL
transmission_rpc-7.0.11.dist-info/METADATA
transmission_rpc-7.0.11.dist-info/RECORD
