Metadata-Version: 2.1
Name: transmission-rpc
Version: 7.0.11
Summary: Python module that implements the Transmission bittorent client JSON-RPC protocol
Keywords: transmission,rpc
Author-email: trim21 <trim21me@gmail.com>
Requires-Python: ~=3.8
Classifier: Intended Audience :: Developers
Classifier: Development Status :: 4 - Beta
Classifier: License :: OSI Approved :: MIT License
Classifier: Programming Language :: Python :: 3 :: Only
Classifier: Programming Language :: Python :: 3.8
Classifier: Programming Language :: Python :: 3.9
Classifier: Programming Language :: Python :: 3.10
Classifier: Programming Language :: Python :: 3.11
Classifier: Programming Language :: Python :: 3.12
Classifier: Programming Language :: Python :: Implementation :: CPython
Classifier: Programming Language :: Python :: Implementation :: PyPy
Requires-Dist: requests~=2.23
Requires-Dist: typing-extensions>=4.5.0
Requires-Dist: pre-commit==3.8.0 ; extra == "dev" and ( python_version >= "3.9")
Requires-Dist: yarl==1.9.4 ; extra == "dev"
Requires-Dist: pytest==8.3.2 ; extra == "dev"
Requires-Dist: pytest-github-actions-annotate-failures==0.2.0 ; extra == "dev"
Requires-Dist: coverage==7.6.0 ; extra == "dev"
Requires-Dist: mypy==1.11.1 ; extra == "dev"
Requires-Dist: types-requests==2.32.0.20240712 ; extra == "dev"
Requires-Dist: sphinx>=7,<=8 ; extra == "dev" and ( python_version >= "3.9")
Requires-Dist: furo==2024.7.18 ; extra == "dev" and ( python_version >= "3.9")
Requires-Dist: sphinx-copybutton==0.5.2  ; extra == "dev" and ( python_version >= "3.9")
Requires-Dist: sphinx-new-tab-link==0.5.2 ; extra == "dev" and ( python_version >= "3.9")
Requires-Dist: sphinx-github-style==1.2.2  ; extra == "dev" and ( python_version >= "3.9")
Requires-Dist: sphinx-autobuild==2024.4.16  ; extra == "dev" and ( python_version >= "3.9")
Project-URL: Homepage, https://github.com/Trim21/transmission-rpc
Provides-Extra: dev
